[
	{
		"timestamp": "08-18-22 / 04:05 PM",
		"zone": "Bowl",
		"section": "402",
		"row": "OO",
		"quantity": 4,
		"price": 70
	},
	{
		"timestamp": "08-18-22 / 01:00 PM",
		"zone": "Bowl",
		"section": "502",
		"row": "WW",
		"quantity": 4,
		"price": 67.77
	},
	{
		"timestamp": "08-18-22 / 01:00 PM",
		"zone": "Limited View",
		"section": "Bowl 102",
		"row": "QQ",
		"quantity": 2,
		"price": 34.8
	},
	{
		"timestamp": "08-18-22 / 01:00 PM",
		"zone": "Bowl",
		"section": "602",
		"row": "DD",
		"quantity": 1,
		"price": 55
	},
	{
		"timestamp": "08-18-22 / 01:00 PM",
		"zone": "Bowl",
		"section": "802",
		"row": "KK",
		"quantity": 2,
		"price": 68
	},
	{
		"timestamp": "08-18-22 / 01:00 PM",
		"zone": "GA Floor",
		"section": "Floor General Admission",
		"row": "",
		"quantity": 2,
		"price": 110
	},
	{
		"timestamp": "08-18-22 / 12:10 PM",
		"zone": "Bowl",
		"section": "1001",
		"row": "O",
		"quantity": 4,
		"price": 110
	},
	{
		"timestamp": "08-18-22 / 12:10 PM",
		"zone": "GA Floor",
		"section": "Floor General Admission",
		"row": "",
		"quantity": 1,
		"price": 98.7
	},
	{
		"timestamp": "08-18-22 / 12:10 PM",
		"zone": "GA Floor",
		"section": "Floor General Admission",
		"row": "",
		"quantity": 1,
		"price": 99
	},
	{
		"timestamp": "08-18-22 / 11:22 AM",
		"zone": "Bowl",
		"section": "702",
		"row": "AA",
		"quantity": 3,
		"price": 66
	},
	{
		"timestamp": "08-18-22 / 10:34 AM",
		"zone": "GA Floor",
		"section": "Floor General Admission",
		"row": "",
		"quantity": 2,
		"price": 100
	},
	{
		"timestamp": "08-18-22 / 10:34 AM",
		"zone": "GA Floor",
		"section": "Floor General Admission",
		"row": "",
		"quantity": 3,
		"price": 80
	},
	{
		"timestamp": "08-18-22 / 10:34 AM",
		"zone": "Bowl",
		"section": "502",
		"row": "TT",
		"quantity": 5,
		"price": 72
	},
	{
		"timestamp": "08-18-22 / 10:34 AM",
		"zone": "GA Floor",
		"section": "Floor General Admission",
		"row": "",
		"quantity": 2,
		"price": 74
	},
	{
		"timestamp": "08-18-22 / 10:34 AM",
		"zone": "GA Floor",
		"section": "Floor General Admission",
		"row": "",
		"quantity": 5,
		"price": 144
	},
	{
		"timestamp": "08-18-22 / 09:38 AM",
		"zone": "GA Floor",
		"section": "Floor General Admission",
		"row": "",
		"quantity": 2,
		"price": 96.3
	},
	{
		"timestamp": "08-18-22 / 08:02 AM",
		"zone": "Bowl",
		"section": "301",
		"row": "C",
		"quantity": 2,
		"price": 99
	},
	{
		"timestamp": "08-18-22 / 07:19 AM",
		"zone": "GA Floor",
		"section": "Floor General Admission",
		"row": "",
		"quantity": 1,
		"price": 100
	},
	{
		"timestamp": "08-18-22 / 04:55 AM",
		"zone": "Bowl",
		"section": "602",
		"row": "II",
		"quantity": 2,
		"price": 92.27
	},
	{
		"timestamp": "08-18-22 / 01:14 AM",
		"zone": "GA Floor",
		"section": "Floor General Admission",
		"row": "",
		"quantity": 2,
		"price": 80
	},
	{
		"timestamp": "08-17-22 / 11:00 PM",
		"zone": "GA Floor",
		"section": "Floor General Admission",
		"row": "",
		"quantity": 2,
		"price": 74
	},
	{
		"timestamp": "08-17-22 / 11:00 PM",
		"zone": "GA Floor",
		"section": "Floor General Admission",
		"row": "",
		"quantity": 2,
		"price": 108.15
	},
	{
		"timestamp": "08-17-22 / 09:33 PM",
		"zone": "GA Floor",
		"section": "Floor General Admission",
		"row": "",
		"quantity": 2,
		"price": 99
	},
	{
		"timestamp": "08-17-22 / 08:47 PM",
		"zone": "Bowl",
		"section": "602",
		"row": "GG",
		"quantity": 2,
		"price": 75.99
	},
	{
		"timestamp": "08-17-22 / 08:47 PM",
		"zone": "Limited View",
		"section": "Bowl 102",
		"row": "PP",
		"quantity": 6,
		"price": 52.27
	},
	{
		"timestamp": "08-17-22 / 08:47 PM",
		"zone": "Limited View",
		"section": "Bowl 1002",
		"row": "NN",
		"quantity": 3,
		"price": 48.98
	},
	{
		"timestamp": "08-17-22 / 07:55 PM",
		"zone": "Bowl",
		"section": "202",
		"row": "HH",
		"quantity": 5,
		"price": 71
	},
	{
		"timestamp": "08-17-22 / 07:08 PM",
		"zone": "Bowl",
		"section": "601",
		"row": "E",
		"quantity": 2,
		"price": 90
	},
	{
		"timestamp": "08-17-22 / 03:44 PM",
		"zone": "Bowl",
		"section": "302",
		"row": "HH",
		"quantity": 1,
		"price": 40
	},
	{
		"timestamp": "08-17-22 / 02:56 PM",
		"zone": "Bowl",
		"section": "602",
		"row": "WW",
		"quantity": 6,
		"price": 69.99
	},
	{
		"timestamp": "08-17-22 / 01:07 PM",
		"zone": "Bowl",
		"section": "501",
		"row": "D",
		"quantity": 2,
		"price": 100
	},
	{
		"timestamp": "08-17-22 / 01:07 PM",
		"zone": "Bowl",
		"section": "302",
		"row": "MM",
		"quantity": 5,
		"price": 77
	},
	{
		"timestamp": "08-17-22 / 01:07 PM",
		"zone": "GA Floor",
		"section": "Floor General Admission",
		"row": "",
		"quantity": 2,
		"price": 162.18
	},
	{
		"timestamp": "08-17-22 / 12:09 PM",
		"zone": "Bowl",
		"section": "602",
		"row": "OO",
		"quantity": 2,
		"price": 55
	},
	{
		"timestamp": "08-17-22 / 12:09 PM",
		"zone": "GA Floor",
		"section": "Floor General Admission",
		"row": "",
		"quantity": 2,
		"price": 110
	},
	{
		"timestamp": "08-17-22 / 11:21 AM",
		"zone": "Bowl",
		"section": "702",
		"row": "KK",
		"quantity": 2,
		"price": 76
	},
	{
		"timestamp": "08-17-22 / 11:21 AM",
		"zone": "Bowl",
		"section": "802",
		"row": "JJ",
		"quantity": 2,
		"price": 75
	},
	{
		"timestamp": "08-17-22 / 10:36 AM",
		"zone": "Bowl",
		"section": "902",
		"row": "NN",
		"quantity": 1,
		"price": 83
	},
	{
		"timestamp": "08-17-22 / 10:36 AM",
		"zone": "GA Floor",
		"section": "Floor General Admission",
		"row": "",
		"quantity": 2,
		"price": 100
	},
	{
		"timestamp": "08-17-22 / 09:47 AM",
		"zone": "Bowl",
		"section": "302",
		"row": "MM",
		"quantity": 2,
		"price": 71
	},
	{
		"timestamp": "08-17-22 / 09:47 AM",
		"zone": "GA Floor",
		"section": "Floor General Admission",
		"row": "",
		"quantity": 1,
		"price": 99
	},
	{
		"timestamp": "08-17-22 / 08:52 AM",
		"zone": "Bowl",
		"section": "602",
		"row": "DD",
		"quantity": 2,
		"price": 105
	},
	{
		"timestamp": "08-17-22 / 08:03 AM",
		"zone": "GA Floor",
		"section": "Floor General Admission",
		"row": "",
		"quantity": 2,
		"price": 99
	},
	{
		"timestamp": "08-17-22 / 05:19 AM",
		"zone": "GA Floor",
		"section": "Floor General Admission",
		"row": "",
		"quantity": 7,
		"price": 135
	},
	{
		"timestamp": "08-16-22 / 11:37 PM",
		"zone": "Bowl",
		"section": "402",
		"row": "RR",
		"quantity": 2,
		"price": 99
	},
	{
		"timestamp": "08-16-22 / 11:37 PM",
		"zone": "Limited View",
		"section": "Bowl 102",
		"row": "KK",
		"quantity": 2,
		"price": 57.23
	},
	{
		"timestamp": "08-16-22 / 10:49 PM",
		"zone": "GA Floor",
		"section": "Floor General Admission",
		"row": "",
		"quantity": 4,
		"price": 120
	},
	{
		"timestamp": "08-16-22 / 09:56 PM",
		"zone": "GA Floor",
		"section": "Floor General Admission",
		"row": "",
		"quantity": 2,
		"price": 150
	},
	{
		"timestamp": "08-16-22 / 09:56 PM",
		"zone": "GA Floor",
		"section": "Floor General Admission",
		"row": "",
		"quantity": 2,
		"price": 155
	},
	{
		"timestamp": "08-16-22 / 06:49 PM",
		"zone": "Bowl",
		"section": "602",
		"row": "II",
		"quantity": 2,
		"price": 68
	},
	{
		"timestamp": "08-16-22 / 03:35 PM",
		"zone": "GA Floor",
		"section": "Floor General Admission",
		"row": "",
		"quantity": 2,
		"price": 109
	},
	{
		"timestamp": "08-16-22 / 01:55 PM",
		"zone": "Bowl",
		"section": "402",
		"row": "LL",
		"quantity": 2,
		"price": 88.63
	},
	{
		"timestamp": "08-16-22 / 12:16 PM",
		"zone": "GA Floor",
		"section": "Floor General Admission",
		"row": "",
		"quantity": 2,
		"price": 109
	},
	{
		"timestamp": "08-16-22 / 03:15 AM",
		"zone": "Limited View",
		"section": "Bowl 1002",
		"row": "LL",
		"quantity": 2,
		"price": 72.69
	},
	{
		"timestamp": "08-16-22 / 12:42 AM",
		"zone": "Bowl",
		"section": "402",
		"row": "RR",
		"quantity": 2,
		"price": 89
	},
	{
		"timestamp": "08-15-22 / 08:46 PM",
		"zone": "Bowl",
		"section": "302",
		"row": "SS",
		"quantity": 2,
		"price": 65
	},
	{
		"timestamp": "08-15-22 / 08:46 PM",
		"zone": "Limited View",
		"section": "Bowl 102",
		"row": "RR",
		"quantity": 4,
		"price": 50
	},
	{
		"timestamp": "08-15-22 / 05:36 PM",
		"zone": "GA Floor",
		"section": "Floor General Admission",
		"row": "",
		"quantity": 2,
		"price": 178
	},
	{
		"timestamp": "08-15-22 / 03:57 PM",
		"zone": "Limited View",
		"section": "Bowl 102",
		"row": "MM",
		"quantity": 6,
		"price": 52.6
	},
	{
		"timestamp": "08-15-22 / 01:40 PM",
		"zone": "GA Floor",
		"section": "Floor General Admission",
		"row": "",
		"quantity": 2,
		"price": 136.5
	},
	{
		"timestamp": "08-15-22 / 01:40 PM",
		"zone": "GA Floor",
		"section": "Floor General Admission",
		"row": "",
		"quantity": 1,
		"price": 134
	},
	{
		"timestamp": "08-15-22 / 12:50 PM",
		"zone": "Bowl",
		"section": "602",
		"row": "TT",
		"quantity": 3,
		"price": 69.95
	},
	{
		"timestamp": "08-15-22 / 12:50 PM",
		"zone": "GA Floor",
		"section": "Floor General Admission",
		"row": "",
		"quantity": 2,
		"price": 123
	},
	{
		"timestamp": "08-15-22 / 11:57 AM",
		"zone": "Bowl",
		"section": "502",
		"row": "MM",
		"quantity": 2,
		"price": 83
	},
	{
		"timestamp": "08-15-22 / 10:33 AM",
		"zone": "GA Floor",
		"section": "Floor General Admission",
		"row": "",
		"quantity": 1,
		"price": 100
	},
	{
		"timestamp": "08-15-22 / 09:51 AM",
		"zone": "GA Floor",
		"section": "Floor General Admission",
		"row": "",
		"quantity": 2,
		"price": 130.55
	},
	{
		"timestamp": "08-15-22 / 09:51 AM",
		"zone": "GA Floor",
		"section": "Floor General Admission",
		"row": "",
		"quantity": 4,
		"price": 133
	},
	{
		"timestamp": "08-14-22 / 11:47 PM",
		"zone": "GA Floor",
		"section": "Floor General Admission",
		"row": "",
		"quantity": 1,
		"price": 128
	},
	{
		"timestamp": "08-14-22 / 11:01 PM",
		"zone": "GA Floor",
		"section": "Floor General Admission",
		"row": "",
		"quantity": 1,
		"price": 125
	},
	{
		"timestamp": "08-14-22 / 04:31 PM",
		"zone": "Limited View",
		"section": "Bowl 102",
		"row": "OO",
		"quantity": 2,
		"price": 35.79
	},
	{
		"timestamp": "08-14-22 / 12:10 PM",
		"zone": "Bowl",
		"section": "601",
		"row": "K",
		"quantity": 1,
		"price": 115
	},
	{
		"timestamp": "08-14-22 / 11:32 AM",
		"zone": "Limited View",
		"section": "Bowl 1002",
		"row": "OO",
		"quantity": 4,
		"price": 35.79
	},
	{
		"timestamp": "08-14-22 / 12:07 AM",
		"zone": "Bowl",
		"section": "902",
		"row": "BB",
		"quantity": 2,
		"price": 80
	},
	{
		"timestamp": "08-13-22 / 03:49 PM",
		"zone": "GA Floor",
		"section": "Floor General Admission",
		"row": "",
		"quantity": 2,
		"price": 138.6
	},
	{
		"timestamp": "08-13-22 / 02:19 PM",
		"zone": "GA Floor",
		"section": "Floor General Admission",
		"row": "",
		"quantity": 2,
		"price": 128
	},
	{
		"timestamp": "08-12-22 / 10:25 PM",
		"zone": "GA Floor",
		"section": "Floor General Admission",
		"row": "",
		"quantity": 1,
		"price": 130
	},
	{
		"timestamp": "08-12-22 / 11:11 AM",
		"zone": "Bowl",
		"section": "902",
		"row": "JJ",
		"quantity": 2,
		"price": 69.99
	},
	{
		"timestamp": "08-11-22 / 06:16 PM",
		"zone": "GA Floor",
		"section": "Floor General Admission",
		"row": "",
		"quantity": 1,
		"price": 130
	},
	{
		"timestamp": "08-11-22 / 05:31 PM",
		"zone": "Bowl",
		"section": "602",
		"row": "DD",
		"quantity": 6,
		"price": 105
	},
	{
		"timestamp": "08-11-22 / 05:31 PM",
		"zone": "Bowl",
		"section": "501",
		"row": "J",
		"quantity": 2,
		"price": 99.95
	},
	{
		"timestamp": "08-11-22 / 01:34 PM",
		"zone": "Bowl",
		"section": "702",
		"row": "NN",
		"quantity": 2,
		"price": 90
	},
	{
		"timestamp": "08-11-22 / 10:33 AM",
		"zone": "Bowl",
		"section": "602",
		"row": "PP",
		"quantity": 2,
		"price": 89.95
	},
	{
		"timestamp": "08-10-22 / 04:23 PM",
		"zone": "GA Floor",
		"section": "Floor General Admission",
		"row": "",
		"quantity": 2,
		"price": 135
	},
	{
		"timestamp": "08-10-22 / 11:05 AM",
		"zone": "GA Floor",
		"section": "Floor General Admission",
		"row": "",
		"quantity": 2,
		"price": 133
	},
	{
		"timestamp": "08-10-22 / 09:39 AM",
		"zone": "GA Floor",
		"section": "Floor General Admission",
		"row": "",
		"quantity": 2,
		"price": 133
	},
	{
		"timestamp": "08-10-22 / 12:18 AM",
		"zone": "Bowl",
		"section": "902",
		"row": "II",
		"quantity": 6,
		"price": 99.99
	},
	{
		"timestamp": "08-09-22 / 07:13 PM",
		"zone": "Limited View",
		"section": "Bowl 102",
		"row": "XX",
		"quantity": 6,
		"price": 41.42
	},
	{
		"timestamp": "08-09-22 / 11:31 AM",
		"zone": "GA Floor",
		"section": "Floor General Admission",
		"row": "",
		"quantity": 2,
		"price": 127.05
	},
	{
		"timestamp": "08-09-22 / 10:46 AM",
		"zone": "Bowl",
		"section": "902",
		"row": "KK",
		"quantity": 5,
		"price": 69.99
	},
	{
		"timestamp": "08-08-22 / 10:25 PM",
		"zone": "GA Floor",
		"section": "Floor General Admission",
		"row": "",
		"quantity": 2,
		"price": 150
	},
	{
		"timestamp": "08-08-22 / 07:35 PM",
		"zone": "Bowl",
		"section": "302",
		"row": "BB",
		"quantity": 2,
		"price": 99
	},
	{
		"timestamp": "08-08-22 / 06:15 PM",
		"zone": "Bowl",
		"section": "502",
		"row": "DD",
		"quantity": 6,
		"price": 105
	},
	{
		"timestamp": "08-08-22 / 04:52 PM",
		"zone": "Limited View",
		"section": "Bowl 1002",
		"row": "QQ",
		"quantity": 2,
		"price": 38.8
	},
	{
		"timestamp": "08-08-22 / 10:37 AM",
		"zone": "GA Floor",
		"section": "Floor General Admission",
		"row": "",
		"quantity": 1,
		"price": 95
	},
	{
		"timestamp": "08-08-22 / 10:37 AM",
		"zone": "GA Floor",
		"section": "Floor General Admission",
		"row": "",
		"quantity": 1,
		"price": 125
	},
	{
		"timestamp": "08-08-22 / 09:56 AM",
		"zone": "Bowl",
		"section": "502",
		"row": "MM",
		"quantity": 2,
		"price": 85
	},
	{
		"timestamp": "08-07-22 / 11:47 PM",
		"zone": "Bowl",
		"section": "301",
		"row": "C",
		"quantity": 2,
		"price": 107
	},
	{
		"timestamp": "08-07-22 / 07:49 PM",
		"zone": "GA Floor",
		"section": "Floor General Admission",
		"row": "",
		"quantity": 2,
		"price": 133
	},
	{
		"timestamp": "08-07-22 / 06:30 PM",
		"zone": "GA Floor",
		"section": "Floor General Admission",
		"row": "",
		"quantity": 1,
		"price": 95
	},
	{
		"timestamp": "08-06-22 / 07:16 PM",
		"zone": "GA Floor",
		"section": "Floor General Admission",
		"row": "",
		"quantity": 2,
		"price": 138
	},
	{
		"timestamp": "08-04-22 / 09:45 PM",
		"zone": "Bowl",
		"section": "902",
		"row": "NN",
		"quantity": 2,
		"price": 80
	},
	{
		"timestamp": "08-04-22 / 12:14 PM",
		"zone": "Bowl",
		"section": "702",
		"row": "BB",
		"quantity": 4,
		"price": 106.05
	},
	{
		"timestamp": "08-04-22 / 12:14 PM",
		"zone": "GA Floor",
		"section": "Floor General Admission",
		"row": "N/A",
		"quantity": 2,
		"price": 124.25
	},
	{
		"timestamp": "08-04-22 / 12:16 AM",
		"zone": "Bowl",
		"section": "902",
		"row": "QQ",
		"quantity": 4,
		"price": 69.99
	},
	{
		"timestamp": "08-03-22 / 01:23 PM",
		"zone": "Bowl",
		"section": "501",
		"row": "M",
		"quantity": 1,
		"price": 99
	},
	{
		"timestamp": "08-03-22 / 12:01 PM",
		"zone": "GA Floor",
		"section": "Floor General Admission",
		"row": "",
		"quantity": 2,
		"price": 130
	},
	{
		"timestamp": "08-02-22 / 12:55 AM",
		"zone": "Bowl",
		"section": "502",
		"row": "CC",
		"quantity": 6,
		"price": 115
	},
	{
		"timestamp": "08-01-22 / 09:48 PM",
		"zone": "Bowl",
		"section": "1002",
		"row": "XX",
		"quantity": 4,
		"price": 68.9
	},
	{
		"timestamp": "07-31-22 / 10:13 PM",
		"zone": "GA Floor",
		"section": "Floor General Admission",
		"row": "",
		"quantity": 2,
		"price": 128
	},
	{
		"timestamp": "07-31-22 / 12:38 PM",
		"zone": "Bowl",
		"section": "602",
		"row": "II",
		"quantity": 2,
		"price": 84.99
	},
	{
		"timestamp": "07-29-22 / 01:09 PM",
		"zone": "Bowl",
		"section": "302",
		"row": "MM",
		"quantity": 2,
		"price": 60
	},
	{
		"timestamp": "07-28-22 / 08:56 PM",
		"zone": "Bowl",
		"section": "502",
		"row": "II",
		"quantity": 2,
		"price": 89.95
	},
	{
		"timestamp": "07-28-22 / 11:43 AM",
		"zone": "Bowl",
		"section": "602",
		"row": "OO",
		"quantity": 2,
		"price": 80
	},
	{
		"timestamp": "07-28-22 / 11:43 AM",
		"zone": "GA Floor",
		"section": "Floor General Admission",
		"row": "N/A",
		"quantity": 2,
		"price": 135.25
	},
	{
		"timestamp": "07-27-22 / 07:34 PM",
		"zone": "Bowl",
		"section": "902",
		"row": "RR",
		"quantity": 6,
		"price": 69.99
	},
	{
		"timestamp": "07-26-22 / 04:45 PM",
		"zone": "Limited View",
		"section": "Bowl 102",
		"row": "KK",
		"quantity": 2,
		"price": 72.69
	},
	{
		"timestamp": "07-25-22 / 03:42 PM",
		"zone": "Bowl",
		"section": "902",
		"row": "EE",
		"quantity": 2,
		"price": 65
	},
	{
		"timestamp": "07-25-22 / 02:42 PM",
		"zone": "Bowl",
		"section": "802",
		"row": "FF",
		"quantity": 4,
		"price": 106.59
	},
	{
		"timestamp": "07-24-22 / 11:37 PM",
		"zone": "Bowl",
		"section": "502",
		"row": "LL",
		"quantity": 2,
		"price": 104.95
	},
	{
		"timestamp": "07-23-22 / 03:28 PM",
		"zone": "GA Floor",
		"section": "Floor General Admission",
		"row": "",
		"quantity": 2,
		"price": 125
	},
	{
		"timestamp": "07-22-22 / 08:42 PM",
		"zone": "Bowl",
		"section": "502",
		"row": "OO",
		"quantity": 2,
		"price": 89.95
	},
	{
		"timestamp": "07-21-22 / 10:19 PM",
		"zone": "Bowl",
		"section": "902",
		"row": "QQ",
		"quantity": 2,
		"price": 69.95
	},
	{
		"timestamp": "07-21-22 / 06:35 PM",
		"zone": "Bowl",
		"section": "602",
		"row": "PP",
		"quantity": 2,
		"price": 99
	},
	{
		"timestamp": "07-19-22 / 05:44 PM",
		"zone": "Bowl",
		"section": "502",
		"row": "KK",
		"quantity": 2,
		"price": 92.4
	},
	{
		"timestamp": "07-18-22 / 12:53 PM",
		"zone": "Bowl",
		"section": "202",
		"row": "OO",
		"quantity": 5,
		"price": 79.39
	},
	{
		"timestamp": "07-17-22 / 10:45 AM",
		"zone": "Bowl",
		"section": "202",
		"row": "NN",
		"quantity": 2,
		"price": 77
	},
	{
		"timestamp": "07-16-22 / 08:08 PM",
		"zone": "Bowl",
		"section": "502",
		"row": "JJ",
		"quantity": 4,
		"price": 88.2
	},
	{
		"timestamp": "07-14-22 / 09:24 PM",
		"zone": "Limited View",
		"section": "Bowl 102",
		"row": "UU",
		"quantity": 6,
		"price": 61.04
	},
	{
		"timestamp": "07-13-22 / 09:32 PM",
		"zone": "Bowl",
		"section": "902",
		"row": "MM",
		"quantity": 2,
		"price": 55
	},
	{
		"timestamp": "07-09-22 / 12:15 PM",
		"zone": "Bowl",
		"section": "902",
		"row": "PP",
		"quantity": 2,
		"price": 64
	},
	{
		"timestamp": "07-08-22 / 10:44 PM",
		"zone": "Bowl",
		"section": "702",
		"row": "SS",
		"quantity": 6,
		"price": 79
	},
	{
		"timestamp": "07-08-22 / 07:17 PM",
		"zone": "Bowl",
		"section": "502",
		"row": "PP",
		"quantity": 2,
		"price": 65.99
	},
	{
		"timestamp": "07-07-22 / 11:57 AM",
		"zone": "Bowl",
		"section": "602",
		"row": "QQ",
		"quantity": 2,
		"price": 87
	},
	{
		"timestamp": "07-07-22 / 11:57 AM",
		"zone": "Bowl",
		"section": "502",
		"row": "RR",
		"quantity": 2,
		"price": 72
	},
	{
		"timestamp": "07-01-22 / 12:30 PM",
		"zone": "Bowl",
		"section": "1002",
		"row": "XX",
		"quantity": 2,
		"price": 68.9
	},
	{
		"timestamp": "06-28-22 / 01:04 PM",
		"zone": "Bowl",
		"section": "1002",
		"row": "XX",
		"quantity": 4,
		"price": 68.9
	},
	{
		"timestamp": "06-23-22 / 07:55 AM",
		"zone": "Bowl",
		"section": "201",
		"row": "C",
		"quantity": 2,
		"price": 249
	},
	{
		"timestamp": "06-22-22 / 09:35 PM",
		"zone": "Limited View",
		"section": "Bowl 1002",
		"row": "NN",
		"quantity": 3,
		"price": 63.37
	},
	{
		"timestamp": "06-18-22 / 10:56 PM",
		"zone": "GA Floor",
		"section": "Floor General Admission",
		"row": "N/A",
		"quantity": 2,
		"price": 153
	},
	{
		"timestamp": "06-17-22 / 08:22 AM",
		"zone": "Bowl",
		"section": "302",
		"row": "PP",
		"quantity": 2,
		"price": 112
	},
	{
		"timestamp": "06-16-22 / 12:40 PM",
		"zone": "Limited View",
		"section": "Bowl 1002",
		"row": "MM",
		"quantity": 2,
		"price": 63.37
	},
	{
		"timestamp": "06-16-22 / 06:36 AM",
		"zone": "GA Floor",
		"section": "Floor General Admission",
		"row": "1",
		"quantity": 4,
		"price": 184.5
	},
	{
		"timestamp": "06-15-22 / 10:35 AM",
		"zone": "GA Floor",
		"section": "Floor General Admission",
		"row": "",
		"quantity": 4,
		"price": 162.18
	},
	{
		"timestamp": "06-15-22 / 05:50 AM",
		"zone": "GA Floor",
		"section": "Floor General Admission",
		"row": "",
		"quantity": 1,
		"price": 158.99
	},
	{
		"timestamp": "06-15-22 / 02:03 AM",
		"zone": "",
		"section": "GENERAL ADMISSION",
		"row": "1",
		"quantity": 6,
		"price": 194.75
	},
	{
		"timestamp": "06-12-22 / 07:59 PM",
		"zone": "Limited View",
		"section": "Bowl 102",
		"row": "SS",
		"quantity": 2,
		"price": 72
	},
	{
		"timestamp": "06-12-22 / 02:15 PM",
		"zone": "Limited View",
		"section": "Bowl 102",
		"row": "RR",
		"quantity": 4,
		"price": 66.3
	},
	{
		"timestamp": "06-10-22 / 11:25 PM",
		"zone": "GA Floor",
		"section": "Floor General Admission",
		"row": "",
		"quantity": 2,
		"price": 168.92
	},
	{
		"timestamp": "06-10-22 / 05:29 AM",
		"zone": "GA Floor",
		"section": "Floor General Admission",
		"row": "",
		"quantity": 1,
		"price": 159.95
	},
	{
		"timestamp": "06-09-22 / 10:25 PM",
		"zone": "GA Floor",
		"section": "Floor General Admission",
		"row": "",
		"quantity": 1,
		"price": 159.95
	},
	{
		"timestamp": "06-09-22 / 07:23 AM",
		"zone": "GA Floor",
		"section": "Floor General Admission",
		"row": "",
		"quantity": 1,
		"price": 159.95
	},
	{
		"timestamp": "06-09-22 / 12:07 AM",
		"zone": "GA Floor",
		"section": "Floor General Admission",
		"row": "",
		"quantity": 1,
		"price": 159.95
	},
	{
		"timestamp": "06-08-22 / 02:47 AM",
		"zone": "GA Floor",
		"section": "Floor General Admission",
		"row": "",
		"quantity": 1,
		"price": 159.95
	},
	{
		"timestamp": "06-07-22 / 09:23 PM",
		"zone": "Limited View",
		"section": "Bowl 102",
		"row": "LL",
		"quantity": 2,
		"price": 59.8
	},
	{
		"timestamp": "06-07-22 / 08:07 PM",
		"zone": "GA Floor",
		"section": "Floor General Admission",
		"row": "",
		"quantity": 1,
		"price": 159.95
	},
	{
		"timestamp": "06-07-22 / 12:42 PM",
		"zone": "GA Floor",
		"section": "Floor General Admission",
		"row": "",
		"quantity": 1,
		"price": 159.95
	},
	{
		"timestamp": "06-05-22 / 11:57 PM",
		"zone": "GA Floor",
		"section": "Floor General Admission",
		"row": "GA",
		"quantity": 2,
		"price": 135
	},
	{
		"timestamp": "06-05-22 / 02:36 PM",
		"zone": "Bowl",
		"section": "201",
		"row": "A",
		"quantity": 4,
		"price": 276
	},
	{
		"timestamp": "06-05-22 / 12:56 PM",
		"zone": "Bowl",
		"section": "301",
		"row": "J",
		"quantity": 2,
		"price": 200
	},
	{
		"timestamp": "06-04-22 / 02:43 AM",
		"zone": "GA Floor",
		"section": "Floor General Admission",
		"row": "GA",
		"quantity": 2,
		"price": 149
	},
	{
		"timestamp": "06-01-22 / 10:40 PM",
		"zone": "GA Floor",
		"section": "Floor General Admission",
		"row": "GA",
		"quantity": 2,
		"price": 149
	},
	{
		"timestamp": "05-30-22 / 11:41 PM",
		"zone": "GA Floor",
		"section": "Floor General Admission",
		"row": "GA",
		"quantity": 2,
		"price": 149
	},
	{
		"timestamp": "05-30-22 / 07:47 PM",
		"zone": "Bowl",
		"section": "402",
		"row": "AA",
		"quantity": 3,
		"price": 189
	},
	{
		"timestamp": "05-28-22 / 09:19 PM",
		"zone": "GA Floor",
		"section": "Floor General Admission",
		"row": "N/A",
		"quantity": 2,
		"price": 150
	},
	{
		"timestamp": "05-28-22 / 05:33 PM",
		"zone": "Limited View ",
		"section": "Bowl 102 Limited View",
		"row": "SS",
		"quantity": 4,
		"price": 64
	},
	{
		"timestamp": "05-26-22 / 02:37 PM",
		"zone": "Bowl",
		"section": "702",
		"row": "RR",
		"quantity": 2,
		"price": 106.59
	},
	{
		"timestamp": "05-21-22 / 07:38 PM",
		"zone": "Bowl",
		"section": "401",
		"row": "H",
		"quantity": 2,
		"price": 190.94
	},
	{
		"timestamp": "05-21-22 / 02:17 PM",
		"zone": "Bowl",
		"section": "201",
		"row": "A",
		"quantity": 2,
		"price": 309
	},
	{
		"timestamp": "05-19-22 / 11:43 PM",
		"zone": "Bowl",
		"section": "701",
		"row": "L",
		"quantity": 2,
		"price": 144.99
	},
	{
		"timestamp": "05-17-22 / 11:19 AM",
		"zone": "Bowl",
		"section": "701",
		"row": "I",
		"quantity": 2,
		"price": 151.5
	},
	{
		"timestamp": "05-16-22 / 08:36 AM",
		"zone": "Bowl",
		"section": "502",
		"row": "ss",
		"quantity": 2,
		"price": 90
	},
	{
		"timestamp": "05-14-22 / 11:48 PM",
		"zone": "Bowl",
		"section": "701",
		"row": "I",
		"quantity": 3,
		"price": 164.63
	},
	{
		"timestamp": "05-14-22 / 09:53 PM",
		"zone": "GA Floor",
		"section": "Floor General Admission",
		"row": "GA",
		"quantity": 3,
		"price": 151.8
	},
	{
		"timestamp": "05-13-22 / 10:26 PM",
		"zone": "Limited View ",
		"section": "Bowl 102 Limited View",
		"row": "LL",
		"quantity": 2,
		"price": 65.01
	},
	{
		"timestamp": "05-13-22 / 09:48 AM",
		"zone": "GA Floor",
		"section": "Floor General Admission",
		"row": "GA",
		"quantity": 2,
		"price": 149.98
	},
	{
		"timestamp": "05-12-22 / 04:09 PM",
		"zone": "GA Floor",
		"section": "Floor General Admission",
		"row": "GA",
		"quantity": 3,
		"price": 149.98
	},
	{
		"timestamp": "05-11-22 / 02:37 PM",
		"zone": "Bowl",
		"section": "701",
		"row": "A",
		"quantity": 2,
		"price": 263.15
	},
	{
		"timestamp": "05-11-22 / 10:28 AM",
		"zone": "GA Floor",
		"section": "Floor General Admission",
		"row": "GA9",
		"quantity": 2,
		"price": 146.01
	},
	{
		"timestamp": "05-11-22 / 09:39 AM",
		"zone": "Limited View ",
		"section": "Bowl 102 Limited View",
		"row": "LL",
		"quantity": 2,
		"price": 65.01
	},
	{
		"timestamp": "05-10-22 / 04:40 PM",
		"zone": "Bowl",
		"section": "701",
		"row": "A",
		"quantity": 2,
		"price": 166.25
	},
	{
		"timestamp": "05-08-22 / 03:56 PM",
		"zone": "Limited View ",
		"section": "Bowl 1002 Limited View",
		"row": "LL",
		"quantity": 2,
		"price": 65
	},
	{
		"timestamp": "05-08-22 / 01:53 PM",
		"zone": "Bowl",
		"section": "401",
		"row": "I",
		"quantity": 2,
		"price": 169.68
	},
	{
		"timestamp": "05-06-22 / 02:01 PM",
		"zone": "Bowl",
		"section": "702",
		"row": "NN",
		"quantity": 4,
		"price": 117.64
	},
	{
		"timestamp": "05-06-22 / 12:00 AM",
		"zone": "Bowl",
		"section": "201",
		"row": "E",
		"quantity": 3,
		"price": 209
	},
	{
		"timestamp": "05-05-22 / 09:59 PM",
		"zone": "Bowl",
		"section": "901",
		"row": "J",
		"quantity": 6,
		"price": 151.21
	},
	{
		"timestamp": "05-04-22 / 08:47 PM",
		"zone": "Bowl",
		"section": "401",
		"row": "I",
		"quantity": 2,
		"price": 169.68
	},
	{
		"timestamp": "05-03-22 / 09:55 PM",
		"zone": "GA Floor",
		"section": "Floor General Admission",
		"row": "GA",
		"quantity": 2,
		"price": 152.74
	},
	{
		"timestamp": "05-03-22 / 11:10 AM",
		"zone": "GA Floor",
		"section": "Floor General Admission",
		"row": "GA99",
		"quantity": 1,
		"price": 150
	},
	{
		"timestamp": "05-02-22 / 10:45 PM",
		"zone": "Bowl",
		"section": "902",
		"row": "LL",
		"quantity": 2,
		"price": 111.54
	},
	{
		"timestamp": "05-02-22 / 09:34 PM",
		"zone": "Bowl",
		"section": "901",
		"row": "A",
		"quantity": 3,
		"price": 249
	},
	{
		"timestamp": "04-30-22 / 08:21 PM",
		"zone": "GA Floor",
		"section": "Floor General Admission",
		"row": "GA",
		"quantity": 2,
		"price": 152.74
	},
	{
		"timestamp": "04-30-22 / 06:29 PM",
		"zone": "Bowl",
		"section": "401",
		"row": "A",
		"quantity": 2,
		"price": 196.89
	},
	{
		"timestamp": "04-26-22 / 08:08 PM",
		"zone": "GA Floor",
		"section": "Floor General Admission",
		"row": "GA",
		"quantity": 2,
		"price": 152.94
	},
	{
		"timestamp": "04-22-22 / 08:26 PM",
		"zone": "Bowl",
		"section": "701",
		"row": "A",
		"quantity": 2,
		"price": 207.25
	},
	{
		"timestamp": "04-21-22 / 11:35 PM",
		"zone": "Bowl",
		"section": "202",
		"row": "LL",
		"quantity": 2,
		"price": 99
	},
	{
		"timestamp": "04-20-22 / 12:15 AM",
		"zone": "Bowl",
		"section": "702",
		"row": "DD",
		"quantity": 2,
		"price": 115
	},
	{
		"timestamp": "04-17-22 / 04:15 PM",
		"zone": "GA Floor",
		"section": "Floor General Admission",
		"row": "GA",
		"quantity": 2,
		"price": 152.94
	},
	{
		"timestamp": "04-07-22 / 12:10 AM",
		"zone": "Bowl",
		"section": "301",
		"row": "C",
		"quantity": 2,
		"price": 165
	},
	{
		"timestamp": "04-07-22 / 12:10 AM",
		"zone": "GA Floor",
		"section": "Floor General Admission",
		"row": "GA99",
		"quantity": 3,
		"price": 154
	},
	{
		"timestamp": "04-06-22 / 06:05 PM",
		"zone": "Bowl",
		"section": "401",
		"row": "I",
		"quantity": 2,
		"price": 126
	},
	{
		"timestamp": "04-05-22 / 11:03 PM",
		"zone": "Bowl",
		"section": "102",
		"row": "NN",
		"quantity": 1,
		"price": 108.9
	},
	{
		"timestamp": "03-28-22 / 01:00 PM",
		"zone": "Bowl",
		"section": "602",
		"row": "SS",
		"quantity": 4,
		"price": 97
	},
	{
		"timestamp": "03-27-22 / 10:37 PM",
		"zone": "Bowl",
		"section": "901",
		"row": "G",
		"quantity": 2,
		"price": 150.94
	},
	{
		"timestamp": "03-27-22 / 08:21 PM",
		"zone": "GA Floor",
		"section": "Floor General Admission",
		"row": "GA99",
		"quantity": 3,
		"price": 154
	},
	{
		"timestamp": "03-27-22 / 05:19 PM",
		"zone": "Bowl",
		"section": "202",
		"row": "NN",
		"quantity": 2,
		"price": 169.68
	},
	{
		"timestamp": "03-25-22 / 11:47 PM",
		"zone": "Bowl",
		"section": "202",
		"row": "NN",
		"quantity": 4,
		"price": 169.68
	},
	{
		"timestamp": "03-25-22 / 05:31 PM",
		"zone": "Bowl",
		"section": "602",
		"row": "QQ",
		"quantity": 2,
		"price": 95
	},
	{
		"timestamp": "03-25-22 / 01:40 AM",
		"zone": "Bowl",
		"section": "401",
		"row": "K",
		"quantity": 2,
		"price": 133.62
	},
	{
		"timestamp": "03-23-22 / 09:26 PM",
		"zone": "Bowl",
		"section": "701",
		"row": "L",
		"quantity": 2,
		"price": 131.3
	},
	{
		"timestamp": "03-23-22 / 04:36 PM",
		"zone": "Bowl",
		"section": "701",
		"row": "I",
		"quantity": 3,
		"price": 143.42
	},
	{
		"timestamp": "03-23-22 / 02:57 PM",
		"zone": "Bowl",
		"section": "401",
		"row": "J",
		"quantity": 2,
		"price": 135.34
	},
	{
		"timestamp": "03-23-22 / 11:20 AM",
		"zone": "Bowl",
		"section": "502",
		"row": "RR",
		"quantity": 2,
		"price": 95
	},
	{
		"timestamp": "03-23-22 / 09:36 AM",
		"zone": "Bowl",
		"section": "301",
		"row": "A",
		"quantity": 2,
		"price": 205
	},
	{
		"timestamp": "03-19-22 / 05:39 PM",
		"zone": "Bowl",
		"section": "102",
		"row": "NN",
		"quantity": 2,
		"price": 108.9
	},
	{
		"timestamp": "03-16-22 / 02:07 PM",
		"zone": "Bowl",
		"section": "201",
		"row": "A",
		"quantity": 4,
		"price": 199.45
	},
	{
		"timestamp": "03-15-22 / 11:49 PM",
		"zone": "Bowl",
		"section": "701",
		"row": "L",
		"quantity": 2,
		"price": 179.78
	},
	{
		"timestamp": "03-15-22 / 04:51 PM",
		"zone": "GA Floor",
		"section": "Floor General Admission",
		"row": "GA",
		"quantity": 2,
		"price": 158
	},
	{
		"timestamp": "03-15-22 / 02:04 PM",
		"zone": "Bowl",
		"section": "701",
		"row": "L",
		"quantity": 2,
		"price": 151.5
	},
	{
		"timestamp": "03-14-22 / 04:05 PM",
		"zone": "Bowl",
		"section": "202",
		"row": "OO",
		"quantity": 2,
		"price": 104.99
	},
	{
		"timestamp": "03-13-22 / 08:06 PM",
		"zone": "Bowl",
		"section": "401",
		"row": "I",
		"quantity": 2,
		"price": 169.68
	},
	{
		"timestamp": "03-12-22 / 09:03 PM",
		"zone": "GA Floor",
		"section": "Floor General Admission",
		"row": "GA99",
		"quantity": 2,
		"price": 144
	},
	{
		"timestamp": "03-12-22 / 01:52 PM",
		"zone": "Bowl",
		"section": "201",
		"row": "I",
		"quantity": 2,
		"price": 162
	},
	{
		"timestamp": "03-12-22 / 09:35 AM",
		"zone": "Bowl",
		"section": "202",
		"row": "OO",
		"quantity": 2,
		"price": 104.99
	},
	{
		"timestamp": "03-12-22 / 12:05 AM",
		"zone": "Bowl",
		"section": "401",
		"row": "I",
		"quantity": 2,
		"price": 169.68
	},
	{
		"timestamp": "03-11-22 / 05:26 PM",
		"zone": "GA Floor",
		"section": "Floor General Admission",
		"row": "GA99",
		"quantity": 3,
		"price": 144
	},
	{
		"timestamp": "03-11-22 / 10:29 AM",
		"zone": "Bowl",
		"section": "401",
		"row": "M",
		"quantity": 2,
		"price": 155.04
	},
	{
		"timestamp": "03-10-22 / 04:00 PM",
		"zone": "Bowl",
		"section": "401",
		"row": "J",
		"quantity": 2,
		"price": 156.55
	},
	{
		"timestamp": "03-10-22 / 10:52 AM",
		"zone": "Bowl",
		"section": "201",
		"row": "I",
		"quantity": 2,
		"price": 164
	},
	{
		"timestamp": "03-09-22 / 12:50 PM",
		"zone": "GA Floor",
		"section": "Floor General Admission",
		"row": "GA99",
		"quantity": 2,
		"price": 144
	},
	{
		"timestamp": "03-08-22 / 02:01 PM",
		"zone": "Bowl",
		"section": "102",
		"row": "NN",
		"quantity": 3,
		"price": 108.9
	},
	{
		"timestamp": "03-05-22 / 06:51 PM",
		"zone": "GA Floor",
		"section": "Floor General Admission",
		"row": "GA99",
		"quantity": 1,
		"price": 144
	},
	{
		"timestamp": "03-05-22 / 02:03 PM",
		"zone": "Bowl",
		"section": "401",
		"row": "M",
		"quantity": 2,
		"price": 187.68
	},
	{
		"timestamp": "03-04-22 / 09:12 PM",
		"zone": "Bowl",
		"section": "402",
		"row": "OO",
		"quantity": 2,
		"price": 94
	},
	{
		"timestamp": "03-04-22 / 08:26 PM",
		"zone": "GA Floor",
		"section": "Floor General Admission",
		"row": "GA1",
		"quantity": 2,
		"price": 143.98
	},
	{
		"timestamp": "03-04-22 / 06:08 PM",
		"zone": "Bowl",
		"section": "402",
		"row": "OO",
		"quantity": 2,
		"price": 94
	},
	{
		"timestamp": "03-04-22 / 04:46 PM",
		"zone": "Bowl",
		"section": "502",
		"row": "OO",
		"quantity": 2,
		"price": 103.99
	},
	{
		"timestamp": "03-02-22 / 08:03 PM",
		"zone": "Bowl",
		"section": "402",
		"row": "OO",
		"quantity": 2,
		"price": 94
	},
	{
		"timestamp": "03-02-22 / 12:37 PM",
		"zone": "Bowl",
		"section": "402",
		"row": "OO",
		"quantity": 2,
		"price": 94
	},
	{
		"timestamp": "03-01-22 / 12:08 PM",
		"zone": "Bowl",
		"section": "301",
		"row": "A",
		"quantity": 2,
		"price": 199
	},
	{
		"timestamp": "03-01-22 / 12:08 PM",
		"zone": "Bowl",
		"section": "902",
		"row": "BB",
		"quantity": 2,
		"price": 121.2
	},
	{
		"timestamp": "02-28-22 / 09:15 PM",
		"zone": "GA Floor",
		"section": "Floor General Admission",
		"row": "GA1",
		"quantity": 2,
		"price": 144.99
	},
	{
		"timestamp": "02-27-22 / 12:30 PM",
		"zone": "Bowl",
		"section": "501",
		"row": "G",
		"quantity": 2,
		"price": 215.94
	},
	{
		"timestamp": "02-26-22 / 08:50 PM",
		"zone": "Bowl",
		"section": "902",
		"row": "BB",
		"quantity": 2,
		"price": 121.2
	},
	{
		"timestamp": "02-26-22 / 05:50 PM",
		"zone": "Bowl",
		"section": "502",
		"row": "NN",
		"quantity": 2,
		"price": 89
	},
	{
		"timestamp": "02-23-22 / 03:33 PM",
		"zone": "GA Floor",
		"section": "Floor General Admission",
		"row": "GA",
		"quantity": 2,
		"price": 149
	},
	{
		"timestamp": "02-23-22 / 12:23 PM",
		"zone": "GA Floor",
		"section": "Floor General Admission",
		"row": "GA",
		"quantity": 2,
		"price": 125
	}
]